archfx_cloud/__init__.py
archfx_cloud/api/__init__.py
archfx_cloud/api/connection.py
archfx_cloud/api/exceptions.py
archfx_cloud/reports/__init__.py
archfx_cloud/reports/exceptions.py
archfx_cloud/reports/flexible_dictionary.py
archfx_cloud/reports/report.py
archfx_cloud/utils/__init__.py
archfx_cloud/utils/basic.py
archfx_cloud/utils/convert.py
archfx_cloud/utils/main.py
archfx_cloud/utils/slugs.py
archfx_cloud-0.17.0.dist-info/LICENSE
archfx_cloud-0.17.0.dist-info/METADATA
archfx_cloud-0.17.0.dist-info/WHEEL
archfx_cloud-0.17.0.dist-info/top_level.txt
archfx_cloud-0.17.0.dist-info/RECORD
