Metadata-Version: 2.1
Name: archfx-cloud
Version: 0.17.0
Summary: Python client for https://archfx.io
Home-page: https://github.com/iotile/python_archfx_cloud
Author: Arch Systems Inc.
Author-email: info@archsys.io
License: MIT
Keywords: iotile,archfx,arch,iiot,automation
Platform: UNKNOWN
Classifier: Programming Language :: Python
Classifier: Programming Language :: Python :: 3
Classifier: Programming Language :: Python :: 3.7
Classifier: Programming Language :: Python :: 3.8
Classifier: Programming Language :: Python :: 3.9
Classifier: Programming Language :: Python :: 3.10
Classifier: Programming Language :: Python :: Implementation :: PyPy
Classifier: Development Status :: 4 - Beta
Classifier: License :: OSI Approved :: MIT License
Classifier: Operating System :: OS Independent
Classifier: Topic :: Software Development :: Libraries :: Python Modules
Requires-Python: >=3.7,<4
Requires-Dist: requests>=2.21.0
Requires-Dist: python-dateutil
Requires-Dist: msgpack<1.1,>=1.0.2
Requires-Dist: typedargs<2,>=1.1.2
